{
  "CrossExchangeLiquidityService": {
    "Db": {
      "LogsConnString": "DefaultEndpointsProtocol=https;AccountName=lkedevlogs;AccountKey=mhOA//Lv9BvDyIBFqDRNsdSa+hgr2Mix+9dCOAnJUT3EHx0fQrl7itHrEsOcosCcovWNNSw+r5+lYfQ8+H9V4A==",
      "EntitiesConnString": "DefaultEndpointsProtocol=https;AccountName=tradingbotdev;AccountKey=QzghZuCMOgdnjDd2hUw2Li/VMmkyhi+YHW25RMg9q9ESr82HpAPpUNYuJBeJjl7G9kWKJ1by8VRZisFG42p9WQ==",
      "AssetBalanceTableName": "CrossExchangeLiquidityAssetBalances"
    },
    "ExternalOrderBook": {
      "Source": {
        "ConnectionString": "amqp://lykke.history:lykke.history@rabbit-me.lykke-me.svc.cluster.local:5672",
        "ExchangeName": "exchangeconnector.orderBooks",
        "NameOfEndpoint": "CrossExchangeLiquidity"
      },
      "Filter": [
        {
          "Source": "bitfinex",
          "AssetPairIds": [ "ETHBTC" ]
        }
      ]
    },
    "LykkeOrderBook": {
      "Source": {
        "ConnectionString": "amqp://lykke.history:lykke.history@rabbit-me.lykke-me.svc.cluster.local:5672",
        "ExchangeName": "orderbook",
        "NameOfEndpoint": "CrossExchangeLiquidity"
      },
      "Filter": [ "ETHBTC" ]
    },
    "MatchingEngineTrader": {
        "IpEndpoint": {
          "Port": 8888,
          "Host": "me.lykke-me.svc.cluster.local",
          "InternalHost": "me.lykke-me.svc.cluster.local",
          "MaxConnections": 100
        },
        "Retry": {
          "Times": 5,
          "Multiplier": 2,
          "TimeSpan": "00:00:00.100"
        },
        "TimeSpan": "00:00:10",
        "clientId": "00974096-2bda-4a85-85cb-f8883eb1be3c",
        "LimitOrders": {
          "ConnectionString": "amqp://lykke.history:lykke.history@rabbit-me.lykke-me.svc.cluster.local:5672",
          "ExchangeName": "limitorders.clients",
          "NameOfEndpoint": "CrossExchangeLiquidity"
        }
      },
      "VolumePriceFilters": {
        "Count": 5,
        "Assets": [
          {
            "AssetId": "BTC",
            "RiskMarkup": 0.007,
            "UseVolumePart": 0.8,
            "MinVolume": 0.3,
            "MinHalfSpread": 0.005
          },
          {
            "AssetId": "ETH",
            "RiskMarkup": 0.1,
            "UseVolumePart": 0.8,
            "MinVolume": 3,
            "MinHalfSpread": 0.07
          }
        ]
      },
      "AssetsServiceUrl": "http://assets.lykke-service.svc.cluster.local",
      "BalancesServiceUrl": "http://balances.lykke-service.svc.cluster.local",
      "ExternalBalance": {
        "Balances": [
          {
            "Source": "bitfinex",
            "AssetValues": [
              {
                "Asset": "ETH",
                "Value": 1000
              },
              {
                "Asset": "BTC",
                "Value": 100
              }
            ]
          }
        ]
      },
      "LykkeBalance": {
        "clientId": "00974096-2bda-4a85-85cb-f8883eb1be3c",
        "TimeSpan": "00:01:00",
        "AssetIds": [ "ETH", "BTC" ]
      }
    },
    "SlackNotifications": {
      "AzureQueue": {
        "ConnectionString": "DefaultEndpointsProtocol=https;AccountName=lkedevshared;AccountKey=deMBXlOj0telRE7poKY+2P9MwPcSsOJ+1IUqG6xoQ3kdDAMhxzvh22zKAXnlaKyPeF0gpbzgK4k7M9ZLdlTx+w==",
        "QueueName": "slack-notifications"
      },
      "ThrottlingLimitSeconds": 60
    }
  }

